polyencoder/__init__.py
polyencoder/cli.py
polyencoder/polyencode_layer.py
polyencoder/polyencoder.py
polyencoder-0.1.0.dist-info/DESCRIPTION.rst
polyencoder-0.1.0.dist-info/entry_points.txt
polyencoder-0.1.0.dist-info/METADATA
polyencoder-0.1.0.dist-info/metadata.json
polyencoder-0.1.0.dist-info/pbr.json
polyencoder-0.1.0.dist-info/RECORD
polyencoder-0.1.0.dist-info/top_level.txt
polyencoder-0.1.0.dist-info/WHEEL
polyencoder-0.1.0.dist-info/zip-safe
