Metadata-Version: 2.0
Name: polyencoder
Version: 0.1.0
Summary: Encode geo features with the GPolyencoder
Home-page: https://github.com/fitnr/polyencoder
Author: fitnr
Author-email: contact@fakeisthenewreal.org
License: BSD
Keywords: polygons gis mapping
Platform: UNKNOWN
Provides-Extra: layer
Requires-Dist: Fiona; extra == 'layer'
